vibe_binary/__init__.py
vibe_binary/neural_guess.py
vibe_binary/search.py
vibe_binary-0.1.4.dist-info/METADATA
vibe_binary-0.1.4.dist-info/WHEEL
vibe_binary-0.1.4.dist-info/top_level.txt
vibe_binary-0.1.4.dist-info/RECORD
