Metadata-Version: 2.4
Name: vibe-binary
Version: 0.1.4
Summary: Библиотека бинарных алгоритмов с AI-магией
Author-email: Your Name <your.email@example.com>
License: MIT
Project-URL: Homepage, https://github.com/yourusername/vibe-binary
Classifier: Development Status :: 3 - Alpha
Classifier: Intended Audience :: Developers
Classifier: License :: OSI Approved :: MIT License
Classifier: Programming Language :: Python :: 3
Requires-Dist: requests>=2.25.0
Requires-Dist: python-dotenv>=1.0.0
